{
  "title": "收益分账",
  "model": "iotbiz_revenue_share",
  "list": {
    "columns": [
      {
        "field": "biz_type",
        "title": "Biz type",
        "width": 120,
        "render": "tag"
      },
      {
        "field": "session_id",
        "title": "Session id",
        "width": 100
      },
      {
        "field": "receiver_type",
        "title": "Receiver type",
        "width": 120,
        "render": "tag"
      },
      {
        "field": "receiver_id",
        "title": "Receiver id",
        "width": 100
      },
      {
        "field": "amount",
        "title": "Amount",
        "width": 100,
        "render": "money"
      },
      {
        "field": "status",
        "title": "Status",
        "width": 100,
        "render": "tag"
      }
    ],
    "orderBy": {
      "field": "id",
      "direction": "desc"
    },
    "pageSize": 20,
    "rowActions": [
      {
        "type": "view",
        "title": "查看"
      },
      {
        "type": "edit",
        "title": "编辑"
      },
      {
        "type": "delete",
        "title": "删除",
        "confirm": "确认删除？"
      }
    ],
    "headerActions": [
      {
        "type": "create",
        "title": "新增收益分账",
        "icon": "plus"
      }
    ]
  },
  "search": {
    "fields": [
      {
        "field": "receiver_type",
        "title": "Receiver type",
        "type": "input"
      },
      {
        "field": "receiver_id",
        "title": "Receiver id",
        "type": "numberRange"
      },
      {
        "field": "status",
        "title": "Status",
        "type": "input"
      }
    ],
    "showCount": 3
  },
  "form": {
    "groups": [
      {
        "title": "基本信息",
        "columns": 2,
        "fields": [
          {
            "field": "tenant_id",
            "title": "Tenant id",
            "type": "number",
            "required": true
          },
          {
            "field": "biz_type",
            "title": "Biz type",
            "type": "input",
            "required": true
          },
          {
            "field": "biz_id",
            "title": "Biz id",
            "type": "number",
            "required": true
          },
          {
            "field": "session_id",
            "title": "Session id",
            "type": "number",
            "required": true
          },
          {
            "field": "trade_order_id",
            "title": "Trade order id",
            "type": "number",
            "required": true
          },
          {
            "field": "receiver_type",
            "title": "Receiver type",
            "type": "input",
            "required": true
          },
          {
            "field": "receiver_id",
            "title": "Receiver id",
            "type": "number"
          },
          {
            "field": "rule_type",
            "title": "Rule type",
            "type": "input",
            "required": true
          },
          {
            "field": "rate",
            "title": "Rate",
            "type": "number"
          },
          {
            "field": "amount",
            "title": "Amount",
            "type": "number",
            "required": true
          },
          {
            "field": "settle_order_id",
            "title": "Settle order id",
            "type": "number"
          },
          {
            "field": "status",
            "title": "Status",
            "type": "input"
          }
        ]
      }
    ],
    "modes": {
      "create": {
        "fields": [
          "tenant_id",
          "biz_type",
          "biz_id",
          "session_id",
          "trade_order_id",
          "receiver_type",
          "receiver_id",
          "rule_type",
          "rate",
          "amount",
          "settle_order_id",
          "status"
        ]
      },
      "edit": {
        "fields": [
          "tenant_id",
          "biz_type",
          "biz_id",
          "session_id",
          "trade_order_id",
          "receiver_type",
          "receiver_id",
          "rule_type",
          "rate",
          "amount",
          "settle_order_id",
          "status"
        ]
      },
      "view": {
        "fields": [
          "id",
          "tenant_id",
          "biz_type",
          "biz_id",
          "session_id",
          "trade_order_id",
          "receiver_type",
          "receiver_id",
          "rule_type",
          "rate",
          "amount",
          "settle_order_id",
          "status",
          "created_at",
          "updated_at"
        ]
      }
    }
  }
}
