{
  "name": "identity_login_log",
  "table": "identity_login_log",
  "comment": "identity_login_log",
  "primaryKey": "id",
  "columns": [
    {
      "name": "id",
      "type": "bigInteger",
      "label": "Id",
      "required": true,
      "primary": true,
      "autoIncrement": true,
      "index": true
    },
    {
      "name": "tenant_id",
      "type": "bigInteger",
      "label": "Tenant id",
      "required": true,
      "index": true
    },
    {
      "name": "user_id",
      "type": "bigInteger",
      "label": "User id",
      "nullable": true
    },
    {
      "name": "login_type",
      "type": "string",
      "label": "Login type",
      "length": 32,
      "required": true
    },
    {
      "name": "ip",
      "type": "string",
      "label": "Ip",
      "length": 64,
      "nullable": true
    },
    {
      "name": "user_agent",
      "type": "string",
      "label": "User agent",
      "length": 500,
      "nullable": true
    },
    {
      "name": "status",
      "type": "string",
      "label": "Status",
      "length": 32,
      "default": "success"
    },
    {
      "name": "fail_reason",
      "type": "string",
      "label": "Fail reason",
      "length": 255,
      "nullable": true
    },
    {
      "name": "created_at",
      "type": "timestamp",
      "label": "Created at",
      "required": true
    }
  ],
  "indexes": [
    {
      "name": "idx_tenant_user_created",
      "columns": [
        "tenant_id",
        "user_id",
        "created_at"
      ],
      "unique": false
    }
  ],
  "option": {
    "timestamps": true,
    "softDeletes": false
  },
  "dataResource": {
    "resourceCode": "identity_login_log",
    "tenantField": "tenant_id",
    "ownerField": "user_id"
  }
}